styxdefs/__init__.py
styxdefs/dry_runner.py
styxdefs/global_state.py
styxdefs/local_runner.py
styxdefs/types.py
styxdefs-0.6.0.dist-info/WHEEL
styxdefs-0.6.0.dist-info/METADATA
styxdefs-0.6.0.dist-info/RECORD
