Metadata-Version: 2.4
Name: styxdefs
Version: 0.6.0
Summary: Styx definitions and minimal runtime
Author: Florian Rupprecht
Author-email: Florian Rupprecht <33600480+nx10@users.noreply.github.com>
License-Expression: MIT
Requires-Python: >=3.10
